confetti/__init__.py
python_confetti-0.1.0.dist-info/METADATA
python_confetti-0.1.0.dist-info/WHEEL
python_confetti-0.1.0.dist-info/top_level.txt
python_confetti-0.1.0.dist-info/RECORD
