Metadata-Version: 2.4
Name: python-confetti
Version: 0.1.0
Summary: Configure your scripts with magic
Requires-Python: >=3.10
Requires-Dist: pydantic
Requires-Dist: pydantic-settings
Requires-Dist: rich
